drf_lighten/__init__.py
drf_lighten/exceptions.py
drf_lighten/lighteners.py
drf_lighten/parsers.py
drf_lighten/serializers.py
drf_lighten/settings.py
drf_lighten/types.py
drf_lighten/views.py
drf_lighten-0.8.1.dist-info/LICENSE
drf_lighten-0.8.1.dist-info/WHEEL
drf_lighten-0.8.1.dist-info/METADATA
drf_lighten-0.8.1.dist-info/RECORD
