Metadata-Version: 2.1
Name: drf_lighten
Version: 0.8.1
Summary: A way to remove unwanted fields from a serializer
Author: Henock Tesfaye
Author-email: jupiter.jupiter1@gmail.com
Classifier: License :: OSI Approved :: MIT License
